mercury_ocip_fast/__init__.py
mercury_ocip_fast/client.py
mercury_ocip_fast/exceptions.py
mercury_ocip_fast/pool.py
mercury_ocip_fast/requester.py
mercury_ocip_fast/commands/__init__.py
mercury_ocip_fast/commands/base_command.py
mercury_ocip_fast/commands/commands.py
mercury_ocip_fast/libs/__init__.py
mercury_ocip_fast/libs/basic_types.py
mercury_ocip_fast/libs/types.py
mercury_ocip_fast/utils/__init__.py
mercury_ocip_fast/utils/defines.py
mercury_ocip_fast/utils/parser.py
mercury_ocip_fast-1.0.0.dist-info/licenses/LICENSE
mercury_ocip_fast-1.0.0.dist-info/METADATA
mercury_ocip_fast-1.0.0.dist-info/WHEEL
mercury_ocip_fast-1.0.0.dist-info/top_level.txt
mercury_ocip_fast-1.0.0.dist-info/RECORD
