Metadata-Version: 2.4
Name: mercury-ocip-fast
Version: 1.0.0
Summary: Asynchronous Python SDK for BroadWorks OCI (Open Client Interface) API
Author-email: Jordan Prescott <devteam@fourteenip.com>, Michael Clarke <devteam@fourteenip.com>, Billy Kelly <devteam@fourteenip.com>
License: MIT License
Keywords: broadworks,oci,telephony,voip,sdk,api,mercury,async,asynchronous
Classifier: Development Status :: 4 - Beta
Classifier: Intended Audience :: Developers
Classifier: Intended Audience :: System Administrators
Classifier: License :: OSI Approved :: MIT License
Classifier: Programming Language :: Python
Classifier: Programming Language :: Python :: 3
Classifier: Programming Language :: Python :: 3.12
Classifier: Programming Language :: Python :: 3.13
Classifier: Operating System :: OS Independent
Classifier: Topic :: Software Development :: Libraries :: Python Modules
Classifier: Topic :: Communications :: Telephony
Classifier: Topic :: Software Development :: Libraries
Classifier: Topic :: Utilities
Requires-Python: >=3.12
License-File: LICENSE
Requires-Dist: attrs>=21.4.0
Requires-Dist: xmltodict>=1.0.2
Dynamic: license-file
